Selenium2Library/__init__.py
Selenium2Library/version.py
Selenium2Library/webdrivermonkeypatches.py
Selenium2Library/keywords/__init__.py
Selenium2Library/keywords/_browsermanagement.py
Selenium2Library/keywords/_cookie.py
Selenium2Library/keywords/_element.py
Selenium2Library/keywords/_formelement.py
Selenium2Library/keywords/_javascript.py
Selenium2Library/keywords/_logging.py
Selenium2Library/keywords/_runonfailure.py
Selenium2Library/keywords/_screenshot.py
Selenium2Library/keywords/_selectelement.py
Selenium2Library/keywords/_tableelement.py
Selenium2Library/keywords/_waiting.py
Selenium2Library/keywords/_webkeywords.py
Selenium2Library/keywords/keywordgroup.py
Selenium2Library/locators/__init__.py
Selenium2Library/locators/customlocator.py
Selenium2Library/locators/elementfinder.py
Selenium2Library/locators/tableelementfinder.py
Selenium2Library/locators/windowmanager.py
Selenium2Library/utils/__init__.py
Selenium2Library/utils/browsercache.py
Selenium2Library/utils/librarylistener.py
Selenium2Library/utils/events/__init__.py
Selenium2Library/utils/events/event.py
Selenium2Library/utils/events/scope_event.py
Selenium2Library/resources/firefoxprofile/localstore.rdf
Selenium2Library/resources/firefoxprofile/prefs.js
robotframework_weblibrary-2.0.2.dev4.dist-info/top_level.txt
robotframework_weblibrary-2.0.2.dev4.dist-info/pbr.json
robotframework_weblibrary-2.0.2.dev4.dist-info/METADATA
robotframework_weblibrary-2.0.2.dev4.dist-info/DESCRIPTION.rst
robotframework_weblibrary-2.0.2.dev4.dist-info/metadata.json
robotframework_weblibrary-2.0.2.dev4.dist-info/WHEEL
robotframework_weblibrary-2.0.2.dev4.dist-info/RECORD
