Metadata-Version: 2.0
Name: robotframework-weblibrary
Version: 2.0.2.dev4
Summary: Web testing library for Robot Framework Extended with Selenium2Library
Home-page: https://github.com/Netease-AutoTest/robotframework-weblibrary
Author: Subscription QA
Author-email: longmazhanfeng@gmail.com
License: Apache License 2.0
Platform: UNKNOWN
Classifier: Environment :: Console
Classifier: Intended Audience :: Developers
Classifier: Operating System :: OS Independent
Classifier: Programming Language :: Python :: 2.7
